Metadata-Version: 2.1
Name: ProtParCon
Version: 3.1
Summary: ProtParCon - A framework for framework for processing
Home-page: https://github.com/iBiology/ProtParCon
Author: FEI YUAN
Author-email: yuanfeifuzzy@gmail.com
License: MIT
Keywords: phylogeny tree alignment simulation biology bioinformatics
Platform: UNKNOWN
Classifier: Development Status :: 3 - Alpha
Classifier: Environment :: Console
Classifier: Intended Audience :: Developers
Classifier: Intended Audience :: Science/Research
Classifier: License :: OSI Approved :: MIT License
Classifier: Natural Language :: English
Classifier: Programming Language :: Python :: 3.4
Classifier: Topic :: Scientific/Engineering :: Bio-Informatics
Requires-Dist: biopython (>=1.71)
